phasi_kit/__init__.py
phasi_kit/async_client.py
phasi_kit/cache.py
phasi_kit/client.py
phasi_kit/models.py
phasi_kit/parser.py
phasi_kit/result.py
phasi_kit/router.py
phasi_kit/validators.py
phasi_kit-0.2.2.dist-info/METADATA
phasi_kit-0.2.2.dist-info/WHEEL
phasi_kit-0.2.2.dist-info/licenses/LICENSE
phasi_kit-0.2.2.dist-info/RECORD
