Metadata-Version: 2.4
Name: phasi-kit
Version: 0.2.2
Summary: Thai VAT tax ID lookup with 10/13-digit support (RD VATINFO)
Project-URL: Homepage, https://example.com/phasi-kit
Project-URL: Repository, https://example.com/phasi-kit.git
Author: phasi-kit maintainers
License:                                  Apache License
License-File: LICENSE
Classifier: License :: OSI Approved :: Apache Software License
Classifier: Operating System :: OS Independent
Classifier: Programming Language :: Python :: 3
Classifier: Programming Language :: Python :: 3 :: Only
Classifier: Programming Language :: Python :: 3.10
Classifier: Programming Language :: Python :: 3.11
Classifier: Programming Language :: Python :: 3.12
Requires-Python: >=3.10
Requires-Dist: beautifulsoup4>=4.12
Requires-Dist: httpx>=0.27
Requires-Dist: loguru>=0.7
Provides-Extra: test
Requires-Dist: pytest-asyncio>=0.21.0; extra == 'test'
Requires-Dist: pytest>=7.0; extra == 'test'
